{
	"@type":"Hierarchy",
	"Name":"location",
	"Elements":
	[
		{
			"Name":"Argentina",
			"Type":"Numeric"
		},
		{
			"Name":"Belgium",
			"Type":"Numeric"
		},
		{
			"Name":"Brazil",
			"Type":"Numeric"
		},
		{
			"Name":"Canada",
			"Type":"Numeric"
		},
		{
			"Name":"Chile",
			"Type":"Numeric"
		},
		{
			"Name":"Denmark",
			"Type":"Numeric"
		},
		{
			"Name":"France",
			"Type":"Numeric"
		},
		{
			"Name":"Germany",
			"Type":"Numeric"
		},
		{
			"Name":"Great Britain",
			"Type":"Numeric"
		},
		{
			"Name":"Greece",
			"Type":"Numeric"
		},
		{
			"Name":"Ireland",
			"Type":"Numeric"
		},
		{
			"Name":"Italy",
			"Type":"Numeric"
		},
		{
			"Name":"Luxemburg",
			"Type":"Numeric"
		},
		{
			"Name":"Mexico",
			"Type":"Numeric"
		},
		{
			"Name":"Netherlands",
			"Type":"Numeric"
		},
		{
			"Name":"Norway",
			"Type":"Numeric"
		},
		{
			"Name":"Portugal",
			"Type":"Numeric"
		},
		{
			"Name":"Spain",
			"Type":"Numeric"
		},
		{
			"Name":"Sweden",
			"Type":"Numeric"
		},
		{
			"Name":"United States",
			"Type":"Numeric"
		},
		{
			"Name":"Uruguay",
			"Type":"Numeric"
		}
	],
	"Subsets@Code.links":[]
}